{
  "slug": "blog-4",
  "overview": [
    {
      "p": "TikTok has transcended its reputation as a platform for dance challenges and lip-syncing teens. With over 1.5 billion monthly active users and the highest engagement rates among all social platforms, TikTok represents a goldmine for businesses and creators willing to embrace its unique culture and algorithm."
    }
  ],
  "details": [
    {
      "type": "section",
      "content": [
        {
          "title": "Why TikTok Matters for Your Business",
          "paragraph": [
            {
              "p": "TikTok's algorithm is the most democratic among social platforms—content quality matters more than follower count. A brand-new account can reach millions with the right video, making it ideal for startups, small businesses, and creators looking to establish themselves quickly."
            },
            {
              "p": "The platform's users are also highly engaged, with the average session lasting over 10 minutes. This means if your content captures attention, you have opportunities to build genuine connections with potential customers."
            }
          ]
        }
      ]
    },
    {
      "type": "section",
      "content": [
        {
          "title": "Understanding TikTok's Recommendation Algorithm",
          "paragraph": [
            {
              "p": "TikTok's \"For You Page\" (FYP) algorithm analyzes user interactions, video information, and device settings to serve personalized content. The algorithm heavily weighs completion rate, re-watches, shares, and comments. Creating content that encourages these actions is fundamental to success."
            },
            {
              "p": "Unlike other platforms where timing matters significantly, TikTok's algorithm can push older videos weeks or months after posting if they start gaining traction. This \"zombie content\" phenomenon means your videos have multiple opportunities to go viral."
            }
          ]
        }
      ]
    },
    {
      "type": "section",
      "content": [
        {
          "title": "Content Pillars for Business Success on TikTok",
          "paragraph": [
            {
              "p": "<h2 style='font-size: 1.5rem;'>Educational Content</h2>"
            },
            {
              "p": "\"Educational\" doesn't mean boring. The most successful business accounts teach valuable skills, share insider knowledge, or solve common problems—all delivered with entertainment value. Quick tips, industry secrets, and how-to content consistently perform well."
            },
            {
              "p": "<h2 style='font-size: 1.5rem;'>Behind-the-Scenes</h2>"
            },
            {
              "p": "TikTok audiences crave authenticity. Show your process, introduce your team, or reveal what goes into creating your products or services. This transparency builds trust and differentiates you from competitors hiding behind polished corporate facades."
            },
            {
              "p": "<h2 style='font-size: 1.5rem;'>Entertainment and Humor</h2>"
            },
            {
              "p": "Don't underestimate entertainment value, even for serious businesses. Relatable humor, trending challenges (with your unique twist), and playful content often achieve the highest engagement rates and shares."
            },
            {
              "p": "<h2 style='font-size: 1.5rem;'>User-Generated Content</h2>"
            },
            {
              "p": "Feature customer testimonials, showcase user-generated content, or create campaigns encouraging customers to share their experiences. This social proof is incredibly powerful and expands your reach through others' networks."
            }
          ]
        }
      ]
    },
    {
      "type": "section",
      "content": [
        {
          "title": "Professional Editing Techniques for TikTok",
          "paragraph": [
            {
              "p": "<h2 style='font-size: 1.5rem;'>Hook Development</h2>"
            },
            {
              "p": "Your first 1-2 seconds determine whether viewers keep watching or scroll. Use pattern interrupts, bold statements, intriguing questions, or unexpected visuals to stop the scroll immediately."
            },
            {
              "p": "<h2 style='font-size: 1.5rem;'>Editing Rhythm and Pacing</h2>"
            },
            {
              "p": "TikTok audiences expect dynamic pacing. Cut to the beat of your audio, use jump cuts to eliminate pauses, and maintain visual interest with varied camera angles or scene changes every few seconds."
            },
            {
              "p": "<h2 style='font-size: 1.5rem;'>Text and Caption Strategy</h2>"
            },
            {
              "p": "Strategic text overlays make your content accessible and emphasize key points. Keep text concise, use large fonts, and time text appearance with your narration or key visual moments."
            },
            {
              "p": "<h2 style='font-size: 1.5rem;'>Trending Effects and Filters</h2>"
            },
            {
              "p": "While not mandatory, using TikTok's native effects and filters can boost discoverability. The platform often promotes content using new features, giving early adopters an algorithmic advantage."
            }
          ]
        }
      ]
    },
    {
      "type": "section",
      "content": [
        {
          "title": "Audio Strategy: The Heart of TikTok",
          "paragraph": [
            {
              "p": "<h2 style='font-size: 1.5rem;'>Trending Sounds</h2>"
            },
            {
              "p": "Trending audio significantly impacts discoverability. Browse your FYP and trending page to identify rising sounds in your niche. Jump on trends early for maximum impact, but only when they align with your content."
            },
            {
              "p": "<h2 style='font-size: 1.5rem;'>Original Audio</h2>"
            },
            {
              "p": "Creating original sounds can be powerful if they go viral, as every video using your audio links back to your account. However, trending sounds typically offer better immediate reach."
            },
            {
              "p": "<h2 style='font-size: 1.5rem;'>Audio Quality Matters</h2>"
            },
            {
              "p": "Whether using trending sounds or recording voiceovers, audio quality cannot be compromised. Invest in good microphones or professional audio editing to ensure your content sounds as good as it looks."
            }
          ]
        }
      ]
    },
    {
      "type": "section",
      "content": [
        {
          "title": "Optimization Tactics for Maximum Reach",
          "paragraph": [
            {
              "p": "<h2 style='font-size: 1.5rem;'>Caption Writing</h2>"
            },
            {
              "p": "Write captions that encourage comments. Ask questions, create controversy (thoughtfully), or prompt viewers to tag friends. Comments signal engagement to the algorithm, boosting your content's reach."
            },
            {
              "p": "<h2 style='font-size: 1.5rem;'>Hashtag Strategy</h2>"
            },
            {
              "p": "Use 3-5 relevant hashtags, mixing broad reach hashtags with niche-specific ones. Avoid spam hashtags like #FYP or #viral—they don't work and appear desperate. Focus on descriptive, relevant hashtags instead."
            },
            {
              "p": "<h2 style='font-size: 1.5rem;'>Posting Timing</h2>"
            },
            {
              "p": "While TikTok's algorithm is less time-sensitive than other platforms, posting when your target audience is active improves initial engagement, which can snowball into viral reach. Analyze your analytics to identify optimal posting times."
            },
            {
              "p": "<h2 style='font-size: 1.5rem;'>Video Length Optimization</h2>"
            },
            {
              "p": "While TikTok allows 10-minute videos, shorter content (15-30 seconds) typically achieves higher completion rates. However, engaged audiences will watch longer content if it delivers consistent value throughout."
            }
          ]
        }
      ]
    },
    {
      "type": "section",
      "content": [
        {
          "title": "Building a Sustainable TikTok Presence",
          "paragraph": [
            {
              "p": "<h2 style='font-size: 1.5rem;'>Consistency Over Perfection</h2>"
            },
            {
              "p": "Posting consistently (daily or multiple times daily) outperforms sporadic posting of perfect content. The algorithm rewards consistent creators, and regular posting provides more opportunities for viral hits."
            },
            {
              "p": "<h2 style='font-size: 1.5rem;'>Niche Focus</h2>"
            },
            {
              "p": "While experimenting is good, establishing a clear niche helps the algorithm understand who to show your content to. Successful accounts typically focus on specific topics rather than posting random content."
            },
            {
              "p": "<h2 style='font-size: 1.5rem;'>Community Engagement</h2>"
            },
            {
              "p": "Respond to comments, engage with other creators' content, and participate in your niche's community. This engagement signals to TikTok that you're an active, valuable creator worth promoting."
            },
            {
              "p": "<h2 style='font-size: 1.5rem;'>Duets and Stitches</h2>"
            },
            {
              "p": "Leverage TikTok's collaboration features to engage with trending content or other creators. Duets and Stitches can expose your content to entirely new audiences while adding your unique perspective."
            }
          ]
        }
      ]
    },
    {
      "type": "section",
      "content": [
        {
          "title": "Converting TikTok Views into Business Results",
          "paragraph": [
            {
              "p": "<h2 style='font-size: 1.5rem;'>Strategic CTAs</h2>"
            },
            {
              "p": "Direct viewers to take action, whether visiting your website, checking your bio, or following for more content. Make CTAs clear, compelling, and easy to follow."
            },
            {
              "p": "<h2 style='font-size: 1.5rem;'>Link Strategy</h2>"
            },
            {
              "p": "With limited link options, optimize your bio link for conversions. Use link-in-bio tools that offer multiple destinations, or direct traffic to landing pages specifically designed for TikTok audiences."
            },
            {
              "p": "<h2 style='font-size: 1.5rem;'>Content That Sells Without Selling</h2>"
            },
            {
              "p": "The hardest-selling content often performs worst on TikTok. Instead, create value-first content that naturally leads viewers to want your products or services."
            }
          ]
        }
      ]
    },
    {
      "type": "section",
      "content": [
        {
          "title": "Common TikTok Mistakes to Avoid",
          "paragraph": [
            {
              "p": "<h2 style='font-size: 1.5rem;'>Reposting Without Optimization</h2>"
            },
            {
              "p": "Simply reposting YouTube or Instagram content rarely works. TikTok has unique style expectations and technical requirements that demand platform-specific content."
            },
            {
              "p": "<h2 style='font-size: 1.5rem;'>Ignoring Trends</h2>"
            },
            {
              "p": "While you don't need to jump on every trend, completely ignoring them means missing easy opportunities for viral reach. Find trends relevant to your niche and participate thoughtfully."
            },
            {
              "p": "<h2 style='font-size: 1.5rem;'>Overselling</h2>"
            },
            {
              "p": "TikTok users are allergic to traditional advertising. Focus on providing value, entertainment, or education first. Trust and interest must be built before sales messages are effective."
            },
            {
              "p": "<h2 style='font-size: 1.5rem;'>Neglecting Analytics</h2>"
            },
            {
              "p": "TikTok's analytics provide invaluable insights into what works. Regularly review your top-performing content to understand patterns and double down on successful themes."
            }
          ]
        }
      ]
    },
    {
      "type": "section",
      "content": [
        {
          "title": "The Role of Professional Video Editing",
          "paragraph": [
            {
              "p": "While TikTok celebrates authenticity, professional editing elevates your content above amateur competitors. Expert editors understand trending techniques, optimal pacing, and how to balance authenticity with polish."
            },
            {
              "p": "Professional editing ensures your content meets quality standards while maintaining the authentic feel TikTok audiences expect. This combination often means the difference between good performance and viral success."
            }
          ]
        }
      ]
    },
    {
      "type": "section",
      "content": [
        {
          "title": "Future-Proofing Your TikTok Strategy",
          "paragraph": [
            {
              "p": "TikTok continues evolving, with features like longer videos, enhanced shopping capabilities, and improved creator monetization. Creators building strong presences now will benefit most as these features mature."
            },
            {
              "p": "The businesses and creators dominating TikTok in 2026 aren't just following trends—they're creating professionally crafted, strategically planned content that serves both algorithmic requirements and genuine audience needs."
            },
            {
              "p": "Success on TikTok requires understanding both the platform's technical requirements and its cultural expectations. Master both, and you'll unlock unprecedented growth opportunities."
            }
          ]
        }
      ]
    },
    {
      "type": "banner",
      "content": {
        "title": "Ready to leverage TikTok's massive reach?",
        "sub_title": "Professional video editing services can help you create scroll-stopping content that drives real business results, from brand awareness to actual sales.",
        "button_label": "Book a Consultation"
      }
    }
  ]
}